{"StashMax":100,"Settings":{"Attachments":{"Reticle_color":{"_type":"Color3","b":0.5831649303436279,"g":1,"r":0.007569432258605957},"Effect_color":{"_type":"Color3","b":0.45838040113449099,"g":1,"r":0.007569432258605957},"Iron_sight_color":{"_type":"Color3","b":0.487257719039917,"g":1,"r":0.007569432258605957},"Laser_color":{"_type":"Color3","b":0.5359516739845276,"g":1,"r":0.007569432258605957}},"Combinations":{"Inspect":[{"_type":"EnumItem","value":102,"enumType":"KeyCode","name":"F"}],"Switch_sight":[{"_type":"EnumItem","value":116,"enumType":"KeyCode","name":"T"}],"Change_alt_firing_mode":[{"_type":"EnumItem","value":98,"enumType":"KeyCode","name":"B"}]},"Audio":{"Weather":100,"Gun_shot":75,"Ambience":50,"Music":100},"Keybinds":{"Sprint":{"_type":"EnumItem","value":304,"enumType":"KeyCode","name":"LeftShift"},"Interact":{"_type":"EnumItem","value":101,"enumType":"KeyCode","name":"E"},"Emote":{"_type":"EnumItem","value":104,"enumType":"KeyCode","name":"H"},"Change_alt_firing_mode":{"_type":"EnumItem","value":98,"enumType":"KeyCode","name":"B"},"Quick_purchase":{"_type":"EnumItem","value":304,"enumType":"KeyCode","name":"LeftShift"},"Toggle_party_chat":{"_type":"EnumItem","value":103,"enumType":"KeyCode","name":"G"},"Inspect":{"_type":"EnumItem","value":102,"enumType":"KeyCode","name":"F"},"Switch_sight":{"_type":"EnumItem","value":116,"enumType":"KeyCode","name":"T"},"Change_firing_mode":{"_type":"EnumItem","value":118,"enumType":"KeyCode","name":"V"},"Ping":{"_type":"EnumItem","value":121,"enumType":"KeyCode","name":"Y"},"Crouch":{"_type":"EnumItem","value":99,"enumType":"KeyCode","name":"C"},"Leaderboard":{"_type":"EnumItem","value":96,"enumType":"KeyCode","name":"Backquote"},"Reload":{"_type":"EnumItem","value":114,"enumType":"KeyCode","name":"R"},"Melee_heavy_attack":{"_type":"EnumItem","value":116,"enumType":"KeyCode","name":"T"},"Drop_item":{"_type":"EnumItem","value":8,"enumType":"KeyCode","name":"Backspace"},"Inventory":{"_type":"EnumItem","value":9,"enumType":"KeyCode","name":"Tab"},"Camera_lock":{"_type":"EnumItem","value":306,"enumType":"KeyCode","name":"LeftControl"},"Quick_Exit":{"_type":"EnumItem","value":113,"enumType":"KeyCode","name":"Q"},"Block":{"_type":"EnumItem","value":113,"enumType":"KeyCode","name":"Q"},"Lock_door":{"_type":"EnumItem","value":103,"enumType":"KeyCode","name":"G"},"Aim":{"_type":"EnumItem","value":113,"enumType":"KeyCode","name":"Q"}},"Crosshair":{"Crosshair_color":{"_type":"Color3","b":0.12941177189350129,"g":1,"r":0.3176470696926117},"Display_lines":true,"Thickness":2,"Transparency":0.9,"Static":false,"Reticle_size":1,"Length":12,"Hitmarker_transparency":0,"Display_dot":false},"Gameplay":{"Allow_party_invites":true,"Camera_animations":1,"Vibration_feedback":true,"Melee_debug":false,"Toggle_sprint":true,"New_items_fill_the_hotbar":true,"Toggle_aim":false,"FOV":90,"Toggle_crouch":false,"Aim_sensitivity":1,"Walkspeed_affects_FOV":true,"Auto_parkour":true,"Parkour_vaulting":true,"Reload_on_empty":true},"Video":{"Dynamic_leg_frequency":30,"Extra_map_details":true,"Max_blood":10,"Snow":true,"Bullet_holes":false,"Dynamic_leg_animations":false,"EXPERIMENTAL_Region_Culling":true,"Experimental_Performance_Mode":0,"Bullet_impact_FX":0.2,"Wind_shake":true,"Max_bullet_shells":2,"Clouds":true},"Interface":{"Show_performance":true,"Show_party_chat_on_message":true,"Damage_numbers":true,"Paycheck_notifications":true,"Status_transparency":0.1,"Display_stat_modifiers":true,"Valuables_amount_alert":3000,"Display_stamina_percentage":true,"Display_health_percentage":true}},"FirstJoinData":{"GotBlitzCoinReward":true},"DailyRewardsClaimed":{"LastClaimDay":20525,"DailyStreak":0,"Day":0},"DropData":[],"Reputation":0,"BadgeData":[],"Journal":[],"PurchaseData":{"OwnedPasses":[],"PurchaseHistory":[]},"Thirst":92.45000000000043,"StarvationPower":0.025,"FFDuration":120,"Character":{"Inventory":{"Items":[],"Gear":[]},"Body":{"Left Leg":{"isBroken":false,"Health":100,"isMissing":false},"Right Arm":{"isBroken":false,"Health":100,"isMissing":false},"Head":{"isBroken":false,"Health":100,"isMissing":false},"Torso":{"isBroken":false,"Health":100,"isMissing":false},"Right Leg":{"isBroken":false,"Health":100,"isMissing":false},"Left Arm":{"isBroken":false,"Health":100,"isMissing":false}}},"WeaponData":[],"hasJoined":false,"ChallengeData":{"Daily":[{"Type":"Daily","Progress":0,"Desc":"Heal other players using any healing consumable","Completed":false,"LongDesc":"Heal other players using any healing consumable","Goal":15,"Title":"Medic","ID":"{dfba0e1b-e97b-4656-81f5-6a581aff8954}","Conditions":{"OnPlayer":true,"Heal":1},"Trigger":"OnConsume","Reward":{"XP":7056,"Bank":28183}},{"Type":"Daily","Progress":0,"Desc":"Heal yourself","Completed":false,"LongDesc":"Heal yourself using any healing consumable","Goal":14,"Title":"Quick Recovery","ID":"{798ba2a9-32cb-4f7a-93e9-519a07ad55f2}","Conditions":{"OnPlayer":true,"Heal":1,"OnSelf":true},"Trigger":"OnConsume","Reward":{"XP":5488,"Bank":29796}},{"Type":"Daily","Progress":0,"Desc":"Use throwable items","Completed":false,"LongDesc":"Throw any throwable item you may find","Goal":21,"Title":"Utility Specialist","ID":"{7242d06b-5163-43a2-8d62-b42aa3b8bf9e}","Conditions":[],"Trigger":"OnThrow","Reward":{"XP":5725,"Bank":26002}},{"Type":"Daily","Progress":0,"Desc":"Destroy bounty boards while having $500+ bounty","Completed":false,"LongDesc":"Destroy bounty boards while having $500+ bounty","Goal":23,"Title":"Tactical Destruction","ID":"{5f685fd1-941e-4370-a869-797997979dd6}","Conditions":[],"Trigger":"OnBillboardBreak","Reward":{"XP":5510,"Bank":23925}}],"Custom":[],"Weekly":[{"Type":"Weekly","Progress":0,"Desc":"Turn in $3500 worth of bounty cards","Completed":false,"LongDesc":"Turn in $3500 worth of bounty cards at once at any broker","Goal":8,"Title":"Risky Hunter","ID":"{ed1b1d04-5dce-4b66-97c3-81df46736b95}","Conditions":{"Amount":3500},"Trigger":"OnBountyCardTrade","Reward":{"XP":21614,"Bank":107933}},{"Type":"Weekly","Progress":0,"Desc":"Headshot players from 180+ studs","Completed":false,"LongDesc":"Hit headshots on players from 180+ studs away","Goal":10,"Title":"Unrivaled Marksmanship","ID":"{572ce5fe-3c76-46af-bccc-9738d14d7d25}","Conditions":{"OnPlayer":true,"Distance":180,"OnHeadshot":true},"Trigger":"OnDamage","Reward":{"XP":24941,"Bank":124895}},{"Type":"Weekly","Progress":0,"Desc":"Perform a finisher on enemies","Completed":false,"LongDesc":"Perform a finisher on any enemy","Goal":14,"Title":"Cold Blooded","ID":"{22b24acf-7bd0-4d40-8c22-8b8a9a345d6a}","Conditions":[],"Trigger":"OnFinisher","Reward":{"XP":25377,"Bank":86875}},{"Type":"Weekly","Progress":0,"Desc":"Kill players without dying","Completed":false,"LongDesc":"Kill enough players without dying","Goal":14,"Title":"Rampage","ID":"{1ffd7d3e-9d9a-468c-aad9-99370cc634f2}","Conditions":{"OnPlayer":true},"Trigger":"OnKill","Reward":{"XP":24152,"Bank":82896}}],"DailyRefresh":20525,"WeeklyRefresh":2932},"Level":1,"BlitzCredit":6,"Credits":5050,"Bank":1000000,"RewardsClaimed":{"newStarterPack":true},"CombatLogged":false,"DehydrationPower":0.05,"Hunger":96.22000000000021,"State":{"MetBlitz":false,"MetContrabandExchanger":false,"MetScourge":false},"Xp":400,"WeaponLevelData":[],"Cosmetics":{"GamepassData":{"EmoteSlotExpansion":false},"Data":{"Emote":["Cheer","Laugh","Point","Wave","Sit","Sturdy","Griddy","Rushin","Whip","Parker","Baroque","Unforgettable"],"Charm":["Rebel Tag"],"LootBox":[],"Finisher":["Default"],"Pose":["Default"],"Skin":["Tomahawk_Starbreaker"]},"Equipped":{"Finisher":["Default"],"Charm":[],"Emote":[],"Pose":["Default"],"Skin":[]}},"Valuables":50000,"Influence":0,"LastKnownPosition":{"_type":"Vector3","x":-625.087646484375,"y":517.3672485351563,"z":232.87855529785157},"Bounty":0,"Unlocked":{"Stash":0,"Merchant":[]},"Stash":[{"Name":"Red Keycard","UUID":"bf23f91c-f957-473b-87af-76a81645731e","Attributes":{"UsesLeft":1,"DisableDropping":true}},{"Name":"Red Keycard","UUID":"6ef2891d-4100-4b8a-a694-0706a1e68fbf","Attributes":{"UsesLeft":1,"DisableDropping":true}},{"Name":"Green Keycard","UUID":"51d4c0f4-eff0-4cab-98bb-c257b7217871","Attributes":{"UsesLeft":1,"DisableDropping":true}},{"Name":"Green Keycard","UUID":"d3549cc5-7d5e-4c46-b0d8-f28ae5ab8e2b","Attributes":{"UsesLeft":1,"DisableDropping":true}},{"Name":"Green Keycard","UUID":"099dc81f-5349-48cc-8e9e-5f0277a0ab76","Attributes":{"UsesLeft":1,"DisableDropping":true}},{"Attributes":{"DisableDropping":true},"StatusAttributes":{"MagazineCapacity":1,"SpareMagazines":0,"AmmoType":0,"CurrentSight":1,"Magazine":1,"Ammo":0,"Mode":1},"Name":"Red Flare Gun","UUID":"a6624cb1-8f29-4950-825e-e9a37b450998"},{"Attributes":{"Type":"Body","CantTakeOff":true,"DisableDropping":true,"NoHats":true,"Unbreakable":true},"StatusAttributes":{"FullSet":"Bladedancer"},"Name":"Bladedancer Vest","UUID":"b0cc881d-f839-41cd-8983-9da2f5f72cf0"},{"Attributes":{"DisableDropping":true},"StatusAttributes":{"Magazine":4,"Ammo":16,"MagazineCapacity":4,"SpareMagazines":4},"Name":"KS-23","UUID":"18b08e85-9d39-4a92-92c3-9344a04e2ad3"}],"Cash":0}