{"StashMax":100,"Settings":{"Interface":{"Show_performance":true,"Show_party_chat_on_message":true,"Damage_numbers":true,"Paycheck_notifications":true,"Status_transparency":0.1,"Display_health_percentage":true,"Valuables_amount_alert":3000,"Display_stamina_percentage":true,"Display_stat_modifiers":true},"Video":{"Dynamic_leg_frequency":30,"Extra_map_details":true,"Max_blood":10,"Clouds":true,"EXPERIMENTAL_Region_Culling":true,"Dynamic_leg_animations":false,"Bullet_holes":false,"Experimental_Performance_Mode":0,"Bullet_impact_FX":0.2,"Wind_shake":true,"Max_bullet_shells":2,"Snow":true},"Audio":{"Weather":100,"Gun_shot":75,"Ambience":50,"Music":100},"Keybinds":{"Sprint":{"_type":"EnumItem","value":304,"enumType":"KeyCode","name":"LeftShift"},"Interact":{"_type":"EnumItem","value":101,"enumType":"KeyCode","name":"E"},"Emote":{"_type":"EnumItem","value":104,"enumType":"KeyCode","name":"H"},"Change_alt_firing_mode":{"_type":"EnumItem","value":98,"enumType":"KeyCode","name":"B"},"Quick_purchase":{"_type":"EnumItem","value":304,"enumType":"KeyCode","name":"LeftShift"},"Toggle_party_chat":{"_type":"EnumItem","value":103,"enumType":"KeyCode","name":"G"},"Inspect":{"_type":"EnumItem","value":102,"enumType":"KeyCode","name":"F"},"Switch_sight":{"_type":"EnumItem","value":116,"enumType":"KeyCode","name":"T"},"Change_firing_mode":{"_type":"EnumItem","value":118,"enumType":"KeyCode","name":"V"},"Ping":{"_type":"EnumItem","value":121,"enumType":"KeyCode","name":"Y"},"Crouch":{"_type":"EnumItem","value":99,"enumType":"KeyCode","name":"C"},"Reload":{"_type":"EnumItem","value":114,"enumType":"KeyCode","name":"R"},"Aim":{"_type":"EnumItem","value":113,"enumType":"KeyCode","name":"Q"},"Lock_door":{"_type":"EnumItem","value":103,"enumType":"KeyCode","name":"G"},"Drop_item":{"_type":"EnumItem","value":8,"enumType":"KeyCode","name":"Backspace"},"Block":{"_type":"EnumItem","value":113,"enumType":"KeyCode","name":"Q"},"Quick_Exit":{"_type":"EnumItem","value":113,"enumType":"KeyCode","name":"Q"},"Camera_lock":{"_type":"EnumItem","value":306,"enumType":"KeyCode","name":"LeftControl"},"Inventory":{"_type":"EnumItem","value":9,"enumType":"KeyCode","name":"Tab"},"Melee_heavy_attack":{"_type":"EnumItem","value":116,"enumType":"KeyCode","name":"T"},"Leaderboard":{"_type":"EnumItem","value":96,"enumType":"KeyCode","name":"Backquote"}},"Crosshair":{"Crosshair_color":{"_type":"Color3","b":0.12941177189350129,"g":1,"r":0.3176470696926117},"Static":false,"Thickness":2,"Transparency":0.9,"Reticle_size":1,"Hitmarker_transparency":0,"Length":12,"Display_lines":true,"Display_dot":false},"Gameplay":{"Allow_party_invites":true,"Camera_animations":1,"Vibration_feedback":true,"Parkour_vaulting":true,"Melee_debug":false,"Toggle_sprint":false,"Auto_parkour":true,"FOV":70,"Toggle_crouch":false,"Aim_sensitivity":1,"Walkspeed_affects_FOV":true,"Toggle_aim":false,"New_items_fill_the_hotbar":true,"Reload_on_empty":true},"Combinations":{"Inspect":[{"_type":"EnumItem","value":102,"enumType":"KeyCode","name":"F"}],"Switch_sight":[{"_type":"EnumItem","value":116,"enumType":"KeyCode","name":"T"}],"Change_alt_firing_mode":[{"_type":"EnumItem","value":98,"enumType":"KeyCode","name":"B"}]},"Attachments":{"Reticle_color":{"_type":"Color3","b":0,"g":0,"r":1},"Effect_color":{"_type":"Color3","b":0.21568627655506135,"g":0.21568627655506135,"r":1},"Iron_sight_color":{"_type":"Color3","b":0.2980392277240753,"g":0.6039215922355652,"r":0.35686275362968447},"Laser_color":{"_type":"Color3","b":0,"g":0,"r":1}}},"DailyRewardsClaimed":{"LastClaimDay":0,"DailyStreak":0,"Day":0},"DropData":[],"Reputation":0,"BadgeData":[],"Journal":[],"PurchaseData":{"OwnedPasses":[],"PurchaseHistory":[]},"Thirst":98.40000000000009,"StarvationPower":0.025,"Character":{"Inventory":{"Items":[],"Gear":[]},"Body":{"Left Leg":{"isBroken":false,"Health":100,"isMissing":false},"Right Arm":{"isBroken":false,"Health":100,"isMissing":false},"Head":{"isBroken":false,"Health":100,"isMissing":false},"Torso":{"isBroken":false,"Health":100,"isMissing":false},"Left Arm":{"isBroken":false,"Health":100,"isMissing":false},"Right Leg":{"isBroken":false,"Health":100,"isMissing":false}}},"FFDuration":120,"hasJoined":false,"ChallengeData":{"Daily":[{"Type":"Daily","Progress":0,"Desc":"Claim your Paycheck","Completed":false,"LongDesc":"Claim your paycheck from any terminal through the currency tab","Goal":4,"Title":"Pensioner","ID":"{37a619ea-de95-4fb4-a88f-9b1006545ddb}","Conditions":[],"Trigger":"OnPaycheckClaim","Reward":{"XP":5219,"Bank":26307}},{"Type":"Daily","Progress":0,"Desc":"Eliminate players","Completed":false,"LongDesc":"Eliminate any player by doing the most damage","Goal":15,"Title":"Bloodlust","ID":"{565d7808-2f41-4627-948a-c72b63d06060}","Conditions":{"OnPlayer":true},"Trigger":"OnKill","Reward":{"XP":7333,"Bank":24517}},{"Type":"Daily","Progress":0,"Desc":"Use throwable items","Completed":false,"LongDesc":"Throw any throwable item you may find","Goal":25,"Title":"Utility Specialist","ID":"{1b8bb48a-a33c-4646-b51e-eaae8cccbefc}","Conditions":[],"Trigger":"OnThrow","Reward":{"XP":7406,"Bank":22683}},{"Type":"Daily","Progress":0,"Desc":"Destroy bounty boards while having $500+ bounty","Completed":false,"LongDesc":"Destroy bounty boards while having $500+ bounty","Goal":28,"Title":"Tactical Destruction","ID":"{3f3abecd-b56e-4ff5-9494-103fef7fef35}","Conditions":[],"Trigger":"OnBillboardBreak","Reward":{"XP":6017,"Bank":22450}}],"Custom":[],"DailyRefresh":20656,"Weekly":[{"Type":"Weekly","Progress":0,"Desc":"Kill players without dying","Completed":false,"LongDesc":"Kill enough players without dying","Goal":10,"Title":"Rampage","ID":"{64a8e581-f94c-4e52-8fdc-5ee82b353d57}","Conditions":{"OnPlayer":true},"Trigger":"OnKill","Reward":{"XP":23060,"Bank":91183}},{"Type":"Weekly","Progress":0,"Desc":"Turn in $20000 worth of valuables","Completed":false,"LongDesc":"Turn in $20000 worth of valuables at once at any broker","Goal":3,"Title":"Risky Collector","ID":"{2035a792-2386-47a4-99b5-6758d80219ee}","Conditions":{"Amount":20000},"Trigger":"OnValuablesTrade","Reward":{"XP":28711,"Bank":107587}},{"Type":"Weekly","Progress":0,"Desc":"Kill players from 300+ studs","Completed":false,"LongDesc":"Kill any player from 300+ studs away","Goal":10,"Title":"Long shot","ID":"{973e0f05-ef0c-4bab-a8b0-acb83f00a367}","Conditions":{"OnPlayer":true,"Distance":300},"Trigger":"OnKill","Reward":{"XP":24148,"Bank":96174}},{"Type":"Weekly","Progress":0,"Desc":"Perform a finisher on enemies","Completed":false,"LongDesc":"Perform a finisher on any enemy","Goal":12,"Title":"Cold Blooded","ID":"{ae3bae86-c59b-4ca2-a77f-1a8d3288492c}","Conditions":[],"Trigger":"OnFinisher","Reward":{"XP":20577,"Bank":89165}}],"WeeklyRefresh":2950},"Level":1,"BlitzCredit":0,"Bank":1000000,"CombatLogged":false,"Bounty":0,"Unlocked":{"Stash":0,"Merchant":[]},"DehydrationPower":0.05,"RewardsClaimed":[],"Credits":2500,"Xp":0,"WeaponLevelData":[],"Valuables":50000,"State":{"MetBlitz":false,"MetScourge":false,"MetContrabandExchanger":false},"Influence":0,"Cosmetics":{"GamepassData":{"EmoteSlotExpansion":false},"Data":{"Emote":["Cheer","Laugh","Point","Wave","Sit","Sturdy","Griddy","Rushin","Whip","Parker","Baroque","Unforgettable"],"Charm":["Rebel Tag"],"Skin":["Tomahawk_Starbreaker"],"Finisher":["Default"],"Pose":["Default"],"LootBox":[]},"Equipped":{"Finisher":["Default"],"Charm":[],"Skin":[],"Pose":["Default"],"Emote":[]}},"Hunger":99.20000000000005,"Stash":[],"WeaponData":[],"Cash":0}