{"StashMax":100,"Settings":{"Interface":{"Show_performance":true,"Show_party_chat_on_message":true,"Damage_numbers":true,"Paycheck_notifications":true,"Status_transparency":0.1,"Display_health_percentage":true,"Display_stat_modifiers":true,"Display_stamina_percentage":true,"Valuables_amount_alert":3000},"Video":{"Dynamic_leg_frequency":30,"Extra_map_details":true,"Max_blood":10,"Clouds":true,"EXPERIMENTAL_Region_Culling":true,"Dynamic_leg_animations":false,"Bullet_holes":false,"Experimental_Performance_Mode":0,"Bullet_impact_FX":0.2,"Wind_shake":true,"Max_bullet_shells":2,"Snow":true},"Audio":{"Weather":100,"Gun_shot":75,"Ambience":50,"Music":100},"Keybinds":{"Sprint":{"_type":"EnumItem","value":304,"enumType":"KeyCode","name":"LeftShift"},"Interact":{"_type":"EnumItem","value":101,"enumType":"KeyCode","name":"E"},"Emote":{"_type":"EnumItem","value":104,"enumType":"KeyCode","name":"H"},"Change_alt_firing_mode":{"_type":"EnumItem","value":98,"enumType":"KeyCode","name":"B"},"Quick_purchase":{"_type":"EnumItem","value":304,"enumType":"KeyCode","name":"LeftShift"},"Toggle_party_chat":{"_type":"EnumItem","value":103,"enumType":"KeyCode","name":"G"},"Inspect":{"_type":"EnumItem","value":102,"enumType":"KeyCode","name":"F"},"Switch_sight":{"_type":"EnumItem","value":116,"enumType":"KeyCode","name":"T"},"Change_firing_mode":{"_type":"EnumItem","value":118,"enumType":"KeyCode","name":"V"},"Ping":{"_type":"EnumItem","value":121,"enumType":"KeyCode","name":"Y"},"Crouch":{"_type":"EnumItem","value":99,"enumType":"KeyCode","name":"C"},"Aim":{"_type":"EnumItem","value":113,"enumType":"KeyCode","name":"Q"},"Reload":{"_type":"EnumItem","value":114,"enumType":"KeyCode","name":"R"},"Lock_door":{"_type":"EnumItem","value":103,"enumType":"KeyCode","name":"G"},"Drop_item":{"_type":"EnumItem","value":8,"enumType":"KeyCode","name":"Backspace"},"Block":{"_type":"EnumItem","value":113,"enumType":"KeyCode","name":"Q"},"Quick_Exit":{"_type":"EnumItem","value":113,"enumType":"KeyCode","name":"Q"},"Camera_lock":{"_type":"EnumItem","value":306,"enumType":"KeyCode","name":"LeftControl"},"Inventory":{"_type":"EnumItem","value":9,"enumType":"KeyCode","name":"Tab"},"Melee_heavy_attack":{"_type":"EnumItem","value":116,"enumType":"KeyCode","name":"T"},"Leaderboard":{"_type":"EnumItem","value":96,"enumType":"KeyCode","name":"Backquote"}},"Crosshair":{"Crosshair_color":{"_type":"Color3","b":0.12941177189350129,"g":1,"r":0.3176470696926117},"Reticle_size":1,"Thickness":2,"Transparency":0.9,"Display_lines":true,"Hitmarker_transparency":0,"Length":12,"Static":false,"Display_dot":false},"Gameplay":{"Allow_party_invites":true,"Camera_animations":1,"Vibration_feedback":true,"Melee_debug":false,"Toggle_sprint":false,"Parkour_vaulting":true,"Auto_parkour":true,"FOV":70,"Toggle_crouch":false,"New_items_fill_the_hotbar":true,"Walkspeed_affects_FOV":true,"Toggle_aim":false,"Aim_sensitivity":1,"Reload_on_empty":true},"Combinations":{"Inspect":[{"_type":"EnumItem","value":102,"enumType":"KeyCode","name":"F"}],"Switch_sight":[{"_type":"EnumItem","value":116,"enumType":"KeyCode","name":"T"}],"Change_alt_firing_mode":[{"_type":"EnumItem","value":98,"enumType":"KeyCode","name":"B"}]},"Attachments":{"Reticle_color":{"_type":"Color3","b":0,"g":0,"r":1},"Effect_color":{"_type":"Color3","b":0.21568627655506135,"g":0.21568627655506135,"r":1},"Iron_sight_color":{"_type":"Color3","b":0.2980392277240753,"g":0.6039215922355652,"r":0.35686275362968447},"Laser_color":{"_type":"Color3","b":0,"g":0,"r":1}}},"FirstJoinData":{"GotBlitzCoinReward":true},"DailyRewardsClaimed":{"Day":1,"LastClaimDay":20533,"DailyStreak":1},"DropData":[],"Reputation":0,"BadgeData":[],"Unlocked":{"Stash":0,"Merchant":[]},"PurchaseData":{"OwnedPasses":[],"PurchaseHistory":[]},"Thirst":0,"StarvationPower":0.025,"FFDuration":120,"Character":{"Inventory":{"Items":[{"Name":"Lockpick","UUID":"fb7df4b4-98a4-4d32-b8d0-410cef9e1a0e"},{"Name":"Lockpick","UUID":"6b036037-64e6-48cb-91b4-653b60ade519"},{"Name":"Lockpick","UUID":"7856144e-3288-4531-911f-dc8868bc8a91"},{"Name":"Lockpick","UUID":"046f3739-c60d-4952-af20-a3b0cdfc08ea"},{"Name":"Lockpick","UUID":"0404b777-55bb-450d-b3d5-e096439d1a47"},{"Name":"Lockpick","UUID":"18d905c4-6696-4f86-9793-38642c02d7b4"},{"Name":"Commander Leggings","StatusAttributes":{"FullSet":"Commander"},"Attributes":{"Unbreakable":true,"Type":"Legs","NoHats":true,"CantTakeOff":true},"UUID":"6752b6ad-d847-4f71-8cd4-6f1e3e2432bd"},{"Name":"Commander Helmet","StatusAttributes":{"FullSet":"Commander"},"Attributes":{"Unbreakable":true,"Type":"Head","NoHats":true,"CantTakeOff":true},"UUID":"5a8d2d1e-bea7-45a8-8423-ccd4503ab1da"},{"UUID":"d0079e09-7bfe-4089-87c3-74235409c4cf","Name":"RSH-12","StatusAttributes":{"MagazineCapacity":5,"Magazine":5,"AmmoType":1,"Mode":1,"Ammo":20,"CurrentSight":1,"SpareMagazines":4}},{"UUID":"71e23c22-6db6-4c8a-ba7f-100a2d7ffb8d","Name":"Blue Keycard","Attributes":{"UsesLeft":2}},{"Name":"P90-Z","StatusAttributes":{"MagazineCapacity":50,"Magazine":50,"AmmoType":1,"Mode":1,"Ammo":200,"CurrentSight":1,"SpareMagazines":4},"Attributes":{"DisableDropping":true},"UUID":"6bce208c-f923-4a5d-b533-a9294b6bb182"},{"UUID":"ec2d05d3-4b09-4e2f-963f-55384ca1d453","Name":"Blue Keycard","Attributes":{"UsesLeft":2}},{"Name":"Commander Vest","StatusAttributes":{"FullSet":"Commander"},"Attributes":{"Unbreakable":true,"Type":"Body","NoHats":true,"CantTakeOff":true},"UUID":"1d084a35-286d-4413-9b5c-8b9a42e6c844"},{"Name":"Lockpick","UUID":"e9e6b5f7-9de6-4188-8bb5-6688d1be491b"},{"Name":"Photon Blades","StatusAttributes":{"Durability":100},"Attributes":{"Durability":100,"Walkspeed":3},"UUID":"948247d4-2e54-479d-ab01-d9030d1bda38"}],"Gear":[{"Name":"Commander Helmet","StatusAttributes":{"FullSet":"Commander"},"Attributes":{"Unbreakable":true,"Type":"Head","NoHats":true,"CantTakeOff":true},"UUID":"45f662f7-0188-4d2f-9a28-440f254cf8de"},{"Name":"Commander Leggings","StatusAttributes":{"FullSet":"Commander"},"Attributes":{"Unbreakable":true,"Type":"Legs","NoHats":true,"CantTakeOff":true},"UUID":"d233a5ab-3632-4308-b38a-6737a260ef9e"},{"Name":"Commander Vest","StatusAttributes":{"FullSet":"Commander"},"Attributes":{"Unbreakable":true,"Type":"Body","NoHats":true,"CantTakeOff":true},"UUID":"ead2c39b-e0ab-437e-a048-4f9f21eb57af"}]},"Body":{"Left Leg":{"isBroken":false,"Health":100,"isMissing":false},"Right Arm":{"isBroken":false,"Health":100,"isMissing":false},"Head":{"isBroken":false,"Health":100,"isMissing":false},"Torso":{"isBroken":false,"Health":100,"isMissing":false},"Right Leg":{"isBroken":false,"Health":100,"isMissing":false},"Left Arm":{"isBroken":false,"Health":100,"isMissing":false}}},"ChallengeData":{"Daily":[{"Type":"Daily","Progress":0,"Desc":"Use throwable items","Completed":false,"LongDesc":"Throw any throwable item you may find","Title":"Utility Specialist","Goal":12,"ID":"{00a71096-ba76-48c3-906c-a08b3aa5b1de}","Conditions":[],"Trigger":"OnThrow","Reward":{"XP":5363,"Bank":29787}},{"Type":"Daily","Progress":0,"Desc":"Heal yourself","Completed":false,"LongDesc":"Heal yourself using any healing consumable","Title":"Quick Recovery","Goal":17,"ID":"{2fbc11bb-c145-40ea-8336-c0dc8afa891c}","Conditions":{"OnPlayer":true,"Heal":1,"OnSelf":true},"Trigger":"OnConsume","Reward":{"XP":5699,"Bank":22050}},{"Type":"Daily","Progress":0,"Desc":"Claim your Paycheck","Completed":false,"LongDesc":"Claim your paycheck from any terminal through the currency tab","Title":"Pensioner","Goal":3,"ID":"{4f7a38b6-b53f-49b4-8da3-e43bfabde8ae}","Conditions":[],"Trigger":"OnPaycheckClaim","Reward":{"XP":6816,"Bank":24837}},{"Type":"Daily","Progress":0,"Desc":"Revive other players","Completed":false,"LongDesc":"Revive other players","Title":"Guardian Angel","Goal":8,"ID":"{22db517e-2527-4fea-ba31-b686d27a03fe}","Conditions":{"OnPlayer":true},"Trigger":"OnRevive","Reward":{"XP":5028,"Bank":21567}}],"Custom":[],"DailyRefresh":20533,"Weekly":[{"Type":"Weekly","Progress":0,"Desc":"Perform a finisher on enemies","Completed":false,"LongDesc":"Perform a finisher on any enemy","Goal":13,"Title":"Cold Blooded","ID":"{06e2863a-23ac-40df-a099-2c3dd2e753b3}","Conditions":[],"Trigger":"OnFinisher","Reward":{"XP":26861,"Bank":119411}},{"Type":"Weekly","Progress":0,"Desc":"Turn in $20000 worth of valuables","Completed":false,"LongDesc":"Turn in $20000 worth of valuables at once at any broker","Goal":2,"Title":"Risky Collector","ID":"{b83099d1-6f0c-4ab0-bbe6-57663425aa05}","Conditions":{"Amount":20000},"Trigger":"OnValuablesTrade","Reward":{"XP":24042,"Bank":101476}},{"Type":"Weekly","Progress":0,"Desc":"Kill players from 300+ studs","Completed":false,"LongDesc":"Kill any player from 300+ studs away","Goal":9,"Title":"Long shot","ID":"{18d4ab4e-07f0-4b23-954d-b97cb1eb1189}","Conditions":{"OnPlayer":true,"Distance":300},"Trigger":"OnKill","Reward":{"XP":24707,"Bank":78489}},{"Type":"Weekly","Progress":0,"Desc":"Headshot players from 180+ studs","Completed":false,"LongDesc":"Hit headshots on players from 180+ studs away","Goal":12,"Title":"Unrivaled Marksmanship","ID":"{f98c00c8-dd2b-4e0b-a0ed-55d1d2db386f}","Conditions":{"OnPlayer":true,"Distance":180,"OnHeadshot":true},"Trigger":"OnDamage","Reward":{"XP":27355,"Bank":116560}}],"WeeklyRefresh":2933},"hasJoined":false,"Journal":{"Terminals":true,"Merchant":true,"Outlanders":true,"GAMEOVER":true,"About Hunter?":true},"Level":3,"CombatLogged":false,"Bank":1010500,"RewardsClaimed":{"newStarterPack":true},"Bounty":0,"BlitzCredit":7,"DehydrationPower":25,"Credits":8050,"Cosmetics":{"GamepassData":{"EmoteSlotExpansion":false},"Data":{"Emote":["Cheer","Laugh","Point","Wave","Sit","Sturdy","Griddy","Rushin","Whip","Parker","Baroque","Unforgettable"],"Charm":["Rebel Tag"],"Skin":["Tomahawk_Starbreaker","G3_RedSpace"],"Finisher":["Default","Katana","Tomahawk"],"Pose":["Default"],"LootBox":[]},"Equipped":{"Finisher":["Default"],"Charm":[],"Skin":[],"Pose":["Default"],"Emote":[]}},"Xp":5300,"WeaponLevelData":[],"State":{"MetBlitz":false,"MetScourge":false,"MetContrabandExchanger":false},"Valuables":354164,"Influence":0,"LastKnownPosition":{"_type":"Vector3","x":-1350.5543212890626,"y":612.9241333007813,"z":-937.1488647460938},"Hunger":38.18999999999984,"Stash":[{"UUID":"c5b3c58f-cd9d-4e6f-bb58-18b552bfcabd","Name":"Red Keycard","Attributes":{"DisableDropping":true,"UsesLeft":1}},{"UUID":"578dcfd3-c093-4eff-a7ac-da53c0c7a68b","Name":"Red Keycard","Attributes":{"DisableDropping":true,"UsesLeft":1}},{"UUID":"95d525ea-1efc-416b-9545-af18ef59472d","Name":"Green Keycard","Attributes":{"DisableDropping":true,"UsesLeft":1}},{"UUID":"11b22018-817b-4889-8f42-098b0e62c4f2","Name":"Green Keycard","Attributes":{"DisableDropping":true,"UsesLeft":1}},{"UUID":"c82fc77f-004a-4f2f-8e62-eda7be00197e","Name":"Green Keycard","Attributes":{"DisableDropping":true,"UsesLeft":1}},{"Name":"Operator Vest","StatusAttributes":{"FullSet":"Operator"},"Attributes":{"Type":"Body","CantTakeOff":true,"Unbreakable":true,"NoHats":true,"DisableDropping":true},"UUID":"2f5b6c8d-0b90-4d78-85cb-45e80530881f"},{"Name":"Commander Leggings","StatusAttributes":{"FullSet":"Commander"},"Attributes":{"Unbreakable":true,"Type":"Legs","NoHats":true,"CantTakeOff":true},"UUID":"98538e50-0092-49cd-b7f5-dc0efaece87c"},{"Name":"Commander Leggings","StatusAttributes":{"FullSet":"Commander"},"Attributes":{"Unbreakable":true,"Type":"Legs","NoHats":true,"CantTakeOff":true},"UUID":"465d733f-347c-439a-9c4a-8a13e013cc12"},{"Name":"Commander Helmet","StatusAttributes":{"FullSet":"Commander"},"Attributes":{"Unbreakable":true,"Type":"Head","NoHats":true,"CantTakeOff":true},"UUID":"94516916-a4a2-4ff7-b985-6c44783f508c"},{"Name":"Commander Helmet","StatusAttributes":{"FullSet":"Commander"},"Attributes":{"Unbreakable":true,"Type":"Head","NoHats":true,"CantTakeOff":true},"UUID":"2c7b99f3-abba-4c9f-af1e-f272d23d7fb9"},{"Name":"Commander Vest","StatusAttributes":{"FullSet":"Commander"},"Attributes":{"Unbreakable":true,"Type":"Body","NoHats":true,"CantTakeOff":true},"UUID":"c7b22a51-a253-44b8-a474-2fcb605a5ed1"},{"Name":"Commander Vest","StatusAttributes":{"FullSet":"Commander"},"Attributes":{"Unbreakable":true,"Type":"Body","NoHats":true,"CantTakeOff":true},"UUID":"505e38f7-e481-46b5-b542-ef91553e5fb4"},{"UUID":"ee75a35a-b124-4836-a3a7-b4b9bfce9c21","Name":"Purple Keycard","Attributes":{"UsesLeft":1}},{"UUID":"9460a2dc-6cfc-4a24-8753-ea2772f7f5ea","Name":"RSH-12","StatusAttributes":{"MagazineCapacity":5,"Magazine":5,"AmmoType":1,"Mode":1,"Ammo":20,"CurrentSight":1,"SpareMagazines":4}},{"Name":"Green Flare Gun","StatusAttributes":{"MagazineCapacity":1,"Magazine":0,"AmmoType":0,"Mode":1,"Ammo":0,"CurrentSight":1,"SpareMagazines":0},"Attributes":{"DisableDropping":true},"UUID":"b03ce021-6549-49b5-af84-d39404f0bd0b"},{"UUID":"559256ec-5fe7-4517-b13b-0df497cdbfaa","Name":"Blue Keycard","Attributes":{"UsesLeft":2}},{"UUID":"4a1d8da8-a67e-454d-9300-d63ef57d56d0","Name":"Blue Keycard","Attributes":{"UsesLeft":2}},{"UUID":"1e07b00f-91a1-43ff-b698-0186121d1d3d","Name":"Blue Keycard","Attributes":{"UsesLeft":2}},{"UUID":"379f026d-6bc4-4953-b2a4-5690bc35624a","Name":"Green Keycard","Attributes":{"UsesLeft":1}},{"UUID":"62c72abb-8bf8-4069-8005-6ca5c6690d85","Name":"Orange Keycard","Attributes":{"UsesLeft":1}},{"UUID":"bdc66e47-ed12-46e6-801f-39b8e24d6bf0","Name":"Orange Keycard","Attributes":{"UsesLeft":1}},{"UUID":"e26ade67-cc8e-4634-87ed-2b6cdcaa70e0","Name":"Orange Keycard","Attributes":{"UsesLeft":1}},{"UUID":"786de588-5bcc-45c3-97b4-8fcbe91640bc","Name":"Orange Keycard","Attributes":{"UsesLeft":1}},{"UUID":"dc408043-bc7e-4394-adde-74d67bf945ce","Name":"Orange Keycard","Attributes":{"UsesLeft":1}},{"UUID":"03020979-bbf7-414c-b1ee-339070e67f6e","Name":"Orange Keycard","Attributes":{"UsesLeft":1}},{"UUID":"2ab66144-df32-499b-804b-9302c12c4542","Name":"Red Keycard","Attributes":{"UsesLeft":1}},{"Name":"Bladedancer Helmet","StatusAttributes":{"FullSet":"Commander"},"Attributes":{"Unbreakable":true,"Type":"Head","NoHats":true,"CantTakeOff":true},"UUID":"1f5e5338-aff8-4d65-8d0f-b62c7c5849c2"},{"UUID":"0df22f5c-ec33-4348-87d4-04408b44e19e","Name":"P90-Z","StatusAttributes":{"MagazineCapacity":50,"Magazine":50,"AmmoType":1,"Mode":1,"Ammo":200,"CurrentSight":1,"SpareMagazines":4}},{"Name":"Photon Blades","StatusAttributes":{"Durability":100},"Attributes":{"Durability":100,"Walkspeed":3},"UUID":"4e250ce4-d059-49a8-8ccd-56a970107808"}],"WeaponData":{"RSH-12":[175,1],"Rendbreaker":[80,1],"SCAR-20":[150,1]},"Cash":638693}