{"StashMax":100,"Settings":{"Attachments":{"Reticle_color":{"_type":"Color3","b":0,"g":0,"r":1},"Effect_color":{"_type":"Color3","b":0.910390317440033,"g":1,"r":0.007569432258605957},"Iron_sight_color":{"_type":"Color3","b":0.2980392277240753,"g":0.6039215922355652,"r":0.35686275362968447},"Laser_color":{"_type":"Color3","b":0,"g":0,"r":1}},"Combinations":{"Inspect":[{"_type":"EnumItem","value":102,"enumType":"KeyCode","name":"F"}],"Switch_sight":[{"_type":"EnumItem","value":116,"enumType":"KeyCode","name":"T"}],"Change_alt_firing_mode":[{"_type":"EnumItem","value":98,"enumType":"KeyCode","name":"B"}]},"Audio":{"Weather":100,"Gun_shot":75,"Ambience":50,"Music":100},"Keybinds":{"Sprint":{"_type":"EnumItem","value":304,"enumType":"KeyCode","name":"LeftShift"},"Interact":{"_type":"EnumItem","value":101,"enumType":"KeyCode","name":"E"},"Emote":{"_type":"EnumItem","value":104,"enumType":"KeyCode","name":"H"},"Change_alt_firing_mode":{"_type":"EnumItem","value":98,"enumType":"KeyCode","name":"B"},"Quick_purchase":{"_type":"EnumItem","value":304,"enumType":"KeyCode","name":"LeftShift"},"Toggle_party_chat":{"_type":"EnumItem","value":103,"enumType":"KeyCode","name":"G"},"Inspect":{"_type":"EnumItem","value":102,"enumType":"KeyCode","name":"F"},"Switch_sight":{"_type":"EnumItem","value":116,"enumType":"KeyCode","name":"T"},"Change_firing_mode":{"_type":"EnumItem","value":118,"enumType":"KeyCode","name":"V"},"Ping":{"_type":"EnumItem","value":121,"enumType":"KeyCode","name":"Y"},"Crouch":{"_type":"EnumItem","value":99,"enumType":"KeyCode","name":"C"},"Leaderboard":{"_type":"EnumItem","value":96,"enumType":"KeyCode","name":"Backquote"},"Aim":{"_type":"EnumItem","value":113,"enumType":"KeyCode","name":"Q"},"Melee_heavy_attack":{"_type":"EnumItem","value":116,"enumType":"KeyCode","name":"T"},"Drop_item":{"_type":"EnumItem","value":8,"enumType":"KeyCode","name":"Backspace"},"Inventory":{"_type":"EnumItem","value":9,"enumType":"KeyCode","name":"Tab"},"Camera_lock":{"_type":"EnumItem","value":306,"enumType":"KeyCode","name":"LeftControl"},"Quick_Exit":{"_type":"EnumItem","value":113,"enumType":"KeyCode","name":"Q"},"Block":{"_type":"EnumItem","value":113,"enumType":"KeyCode","name":"Q"},"Lock_door":{"_type":"EnumItem","value":103,"enumType":"KeyCode","name":"G"},"Reload":{"_type":"EnumItem","value":114,"enumType":"KeyCode","name":"R"}},"Crosshair":{"Crosshair_color":{"_type":"Color3","b":0.12941177189350129,"g":1,"r":0.3176470696926117},"Static":false,"Thickness":2,"Transparency":0.9,"Reticle_size":1,"Display_lines":true,"Length":12,"Hitmarker_transparency":0,"Display_dot":false},"Gameplay":{"Allow_party_invites":true,"Camera_animations":1,"Vibration_feedback":true,"Toggle_sprint":false,"Parkour_vaulting":true,"Aim_sensitivity":1,"Toggle_aim":false,"FOV":70,"Toggle_crouch":false,"New_items_fill_the_hotbar":true,"Walkspeed_affects_FOV":true,"Auto_parkour":true,"Melee_debug":false,"Reload_on_empty":true},"Video":{"Dynamic_leg_frequency":30,"Extra_map_details":true,"Max_blood":10,"Snow":true,"Bullet_holes":false,"Dynamic_leg_animations":false,"EXPERIMENTAL_Region_Culling":true,"Experimental_Performance_Mode":0,"Bullet_impact_FX":0.2,"Wind_shake":true,"Max_bullet_shells":2,"Clouds":true},"Interface":{"Show_performance":true,"Show_party_chat_on_message":true,"Damage_numbers":true,"Paycheck_notifications":true,"Status_transparency":0.1,"Valuables_amount_alert":3000,"Display_stat_modifiers":true,"Display_stamina_percentage":true,"Display_health_percentage":true}},"FirstJoinData":{"GotBlitzCoinReward":true},"DailyRewardsClaimed":{"Day":1,"LastClaimDay":20533,"DailyStreak":1},"DropData":[],"Reputation":0,"BadgeData":{"Welcome":true},"Unlocked":{"Stash":0,"Merchant":[]},"PurchaseData":{"OwnedPasses":[],"PurchaseHistory":[]},"Thirst":21.00000000000371,"StarvationPower":0.025,"FFDuration":120,"Character":{"Inventory":{"Items":[],"Gear":[]},"Body":{"Left Leg":{"isBroken":false,"Health":100,"isMissing":false},"Right Arm":{"isBroken":false,"Health":100,"isMissing":false},"Head":{"isBroken":false,"Health":100,"isMissing":false},"Torso":{"isBroken":false,"Health":100,"isMissing":false},"Right Leg":{"isBroken":false,"Health":100,"isMissing":false},"Left Arm":{"isBroken":false,"Health":100,"isMissing":false}}},"WeaponData":{"AWM":[100,1],"KS-23":[200,1],"Deagle":[150,1],"AK-47":[325,2],"TAC-14":[400,1],"Photon Blades":[140,1],"M4A1":[275,2]},"hasJoined":false,"ChallengeData":{"Daily":[{"Type":"Daily","Progress":0,"Desc":"Heal other players using any healing consumable","Completed":false,"LongDesc":"Heal other players using any healing consumable","Title":"Medic","Goal":10,"ID":"{2143986c-a360-4c54-a6e6-9218b80c8b45}","Conditions":{"OnPlayer":true,"Heal":1},"Trigger":"OnConsume","Reward":{"XP":6439,"Bank":24101}},{"Type":"Daily","Progress":0,"Desc":"Revive other players","Completed":false,"LongDesc":"Revive other players","Title":"Guardian Angel","Goal":5,"ID":"{097dacbd-7e4d-4148-919d-11f15b46cde3}","Conditions":{"OnPlayer":true},"Trigger":"OnRevive","Reward":{"XP":5451,"Bank":24890}},{"Type":"Daily","Progress":0,"Desc":"Perform a finisher on players","Completed":false,"LongDesc":"Perform a finisher on any players","Title":"Executioner","Goal":20,"ID":"{88ff5fb2-5c3e-42c6-9f25-83f2f7e17f26}","Conditions":{"OnPlayer":true},"Trigger":"OnFinish","Reward":{"XP":7366,"Bank":27719}},{"Type":"Daily","Progress":0,"Desc":"Use throwable items","Completed":false,"LongDesc":"Throw any throwable item you may find","Title":"Utility Specialist","Goal":22,"ID":"{ce8abf2c-cde6-41e7-815d-475bdbdc3148}","Conditions":[],"Trigger":"OnThrow","Reward":{"XP":6845,"Bank":24127}}],"Custom":[],"Weekly":[{"Type":"Weekly","Progress":0,"Desc":"Turn in $3500 worth of bounty cards","Completed":false,"LongDesc":"Turn in $3500 worth of bounty cards at once at any broker","Title":"Risky Hunter","Goal":9,"ID":"{4433d183-5cf3-447d-977a-794e559a02e9}","Conditions":{"Amount":3500},"Trigger":"OnBountyCardTrade","Reward":{"XP":23380,"Bank":112710}},{"Type":"Weekly","Progress":0,"Desc":"Kill players without dying","Completed":false,"LongDesc":"Kill enough players without dying","Title":"Rampage","Goal":8,"ID":"{2c4d69a8-de26-4f5d-8e7d-f82080e7190e}","Conditions":{"OnPlayer":true},"Trigger":"OnKill","Reward":{"XP":23213,"Bank":101630}},{"Type":"Weekly","Progress":0,"Desc":"Kill players from 300+ studs","Completed":false,"LongDesc":"Kill any player from 300+ studs away","Title":"Long shot","Goal":6,"ID":"{097c9d9a-08ec-408f-ad23-6ae695562204}","Conditions":{"OnPlayer":true,"Distance":300},"Trigger":"OnKill","Reward":{"XP":28794,"Bank":90491}},{"Type":"Weekly","Progress":0,"Desc":"Turn in $20000 worth of valuables","Completed":false,"LongDesc":"Turn in $20000 worth of valuables at once at any broker","Title":"Risky Collector","Goal":3,"ID":"{ed0bcb6d-6b93-4caa-bc2e-271a27d50554}","Conditions":{"Amount":20000},"Trigger":"OnValuablesTrade","Reward":{"XP":27162,"Bank":94051}}],"DailyRefresh":20533,"WeeklyRefresh":2933},"Level":3,"CombatLogged":false,"Credits":7850,"RewardsClaimed":{"newStarterPack":true},"Bounty":7238,"BlitzCredit":7,"DehydrationPower":4.049999999996292,"Hunger":60.49000000000174,"Bank":1018699,"Xp":4400,"WeaponLevelData":[],"State":{"MetBlitz":false,"MetContrabandExchanger":false,"MetScourge":false},"Valuables":0,"Influence":0,"LastKnownPosition":{"_type":"Vector3","x":-481.0502624511719,"y":446.9241638183594,"z":29.19445037841797},"Cosmetics":{"GamepassData":{"EmoteSlotExpansion":false},"Data":{"Emote":["Cheer","Laugh","Point","Wave","Sit","Sturdy","Griddy","Rushin","Whip","Parker","Baroque","Unforgettable"],"Charm":["Rebel Tag"],"LootBox":[],"Finisher":["Default"],"Pose":["Default"],"Skin":["Tomahawk_Starbreaker"]},"Equipped":{"Finisher":["Default"],"Charm":[],"Emote":[],"Pose":["Default"],"Skin":[]}},"Journal":{"Terminals":true,"Merchant":true,"Brokers":true,"Outlanders":true},"Stash":[{"UUID":"d824614d-8fdd-45e0-9dcb-32200acf4f61","Name":"Red Keycard","Attributes":{"DisableDropping":true,"UsesLeft":1}},{"UUID":"e22c2dfe-3a78-4d63-a75b-75acc70f1133","Name":"Red Keycard","Attributes":{"DisableDropping":true,"UsesLeft":1}},{"UUID":"1d54cf65-bcb8-461a-8517-d0b518e7d49e","Name":"Green Keycard","Attributes":{"DisableDropping":true,"UsesLeft":1}},{"UUID":"f8cf5f11-ac9d-4339-aede-6e11723dab15","Name":"Green Keycard","Attributes":{"DisableDropping":true,"UsesLeft":1}},{"UUID":"0c60ec39-6852-42f6-a7c7-efbbf0ad6837","Name":"Green Keycard","Attributes":{"DisableDropping":true,"UsesLeft":1}},{"Name":"Operator Leggings","StatusAttributes":{"FullSet":"Operator"},"Attributes":{"Type":"Legs","CantTakeOff":true,"Unbreakable":true,"NoHats":true,"DisableDropping":true},"UUID":"fa6d2b5d-f03a-4187-92c1-5d4e7019139f"},{"UUID":"24726f44-aace-468a-83c9-70ea92085d09","Name":"Red Keycard","Attributes":{"UsesLeft":1}},{"UUID":"df6d99bc-06fd-4a1f-b184-2a68449414c7","Name":"Blue Keycard","Attributes":{"UsesLeft":2}},{"Name":"KS-23","StatusAttributes":{"Ammo":15,"Magazine":4,"MagazineCapacity":4,"SpareMagazines":4},"Attributes":{"DisableDropping":true},"UUID":"8b503149-4ab6-466c-8c87-a3fc1f4ea84e"},{"Name":"AWM","StatusAttributes":{"Ammo":13,"Magazine":5,"MagazineCapacity":5,"SpareMagazines":4},"UUID":"43bef5db-9d5f-4449-9fac-650d3f1ba97d","Attachments":{"Sight":"10x Scope","Barrel":"Flash Hider"}},{"Name":"Red Flare Gun","StatusAttributes":{"MagazineCapacity":1,"Magazine":0,"AmmoType":0,"Mode":1,"Ammo":0,"CurrentSight":1,"SpareMagazines":0},"Attributes":{"DisableDropping":true},"UUID":"2fd9caf0-87c1-4c76-a096-7962b3508dba"},{"UUID":"4e1ae857-f1de-4304-9209-276d151d4b6e","Name":"Photon Alternator","StatusAttributes":{"Ammo":90,"Magazine":30,"MagazineCapacity":30,"SpareMagazines":4}},{"Name":"Photon Blades","StatusAttributes":{"Durability":100},"Attributes":{"Durability":100,"Walkspeed":3},"UUID":"ab16e9ab-2bec-456b-b4d7-a8b8bdd4c58e"},{"UUID":"92e38eb3-9fcd-4327-a7f7-e341b018f528","Name":"KS-23","StatusAttributes":{"Ammo":16,"Magazine":4,"MagazineCapacity":4,"SpareMagazines":4}}],"Cash":287297}