{"StashMax":100,"Settings":{"Audio":{"Weather":100,"Gun_shot":75,"Ambience":50,"Music":100},"Keybinds":{"Sprint":{"_type":"EnumItem","value":304,"enumType":"KeyCode","name":"LeftShift"},"Interact":{"_type":"EnumItem","value":101,"enumType":"KeyCode","name":"E"},"Emote":{"_type":"EnumItem","value":104,"enumType":"KeyCode","name":"H"},"Change_alt_firing_mode":{"_type":"EnumItem","value":98,"enumType":"KeyCode","name":"B"},"Quick_purchase":{"_type":"EnumItem","value":304,"enumType":"KeyCode","name":"LeftShift"},"Toggle_party_chat":{"_type":"EnumItem","value":103,"enumType":"KeyCode","name":"G"},"Inspect":{"_type":"EnumItem","value":102,"enumType":"KeyCode","name":"F"},"Switch_sight":{"_type":"EnumItem","value":116,"enumType":"KeyCode","name":"T"},"Change_firing_mode":{"_type":"EnumItem","value":118,"enumType":"KeyCode","name":"V"},"Ping":{"_type":"EnumItem","value":121,"enumType":"KeyCode","name":"Y"},"Crouch":{"_type":"EnumItem","value":99,"enumType":"KeyCode","name":"C"},"Aim":{"_type":"EnumItem","value":113,"enumType":"KeyCode","name":"Q"},"Reload":{"_type":"EnumItem","value":114,"enumType":"KeyCode","name":"R"},"Lock_door":{"_type":"EnumItem","value":103,"enumType":"KeyCode","name":"G"},"Drop_item":{"_type":"EnumItem","value":8,"enumType":"KeyCode","name":"Backspace"},"Block":{"_type":"EnumItem","value":113,"enumType":"KeyCode","name":"Q"},"Quick_Exit":{"_type":"EnumItem","value":113,"enumType":"KeyCode","name":"Q"},"Camera_lock":{"_type":"EnumItem","value":306,"enumType":"KeyCode","name":"LeftControl"},"Inventory":{"_type":"EnumItem","value":9,"enumType":"KeyCode","name":"Tab"},"Melee_heavy_attack":{"_type":"EnumItem","value":116,"enumType":"KeyCode","name":"T"},"Leaderboard":{"_type":"EnumItem","value":96,"enumType":"KeyCode","name":"Backquote"}},"MobileButtons":{"FPS_Position_Y":0,"Action1_Size":1,"Action2_Position_X":0,"Action5_Position_Y":0,"Action0_Size":1,"Action4_Position_X":170,"CameraLock_Position_X":30,"CameraLock_Position_Y":0,"Sprint_Position_Y":36,"Action4_Size":1,"Action1_Position_X":50,"Action0_Position_X":0,"Jump_Position_X":0,"Crouch_Position_Y":0,"FPS_Position_X":0,"Crouch_Size":1,"Jump_Position_Y":0,"Sprint_Position_X":202,"FPS_Size":1,"Action5_Position_X":176,"Action0_Position_Y":0,"Action2_Position_Y":0,"Sprint_Size":2.299999952316284,"CameraLock_Size":1,"Action4_Position_Y":0,"Action3_Size":1,"Action5_Size":1,"Jump_Size":1,"Crouch_Position_X":0,"Action3_Position_X":0,"Action3_Position_Y":0,"Action1_Position_Y":0,"Action2_Size":1},"Attachments":{"Reticle_color":{"_type":"Color3","b":1,"g":0.31433939933776858,"r":0.007569491863250732},"Effect_color":{"_type":"Color3","b":1,"g":0.17884057760238648,"r":0.007569491863250732},"Iron_sight_color":{"_type":"Color3","b":0.6039215922355652,"g":0.004571379628032446,"r":0.04943479225039482},"Laser_color":{"_type":"Color3","b":1,"g":0.2310333251953125,"r":0.007569491863250732}},"Interface":{"Show_performance":true,"Show_party_chat_on_message":true,"Damage_numbers":true,"Paycheck_notifications":true,"Status_transparency":0.1,"Display_health_percentage":true,"Display_stat_modifiers":true,"Display_stamina_percentage":true,"Valuables_amount_alert":3000},"Video":{"Dynamic_leg_frequency":30,"Extra_map_details":true,"Max_blood":10,"Clouds":true,"EXPERIMENTAL_Region_Culling":true,"Dynamic_leg_animations":false,"Bullet_holes":false,"Experimental_Performance_Mode":0,"Bullet_impact_FX":0.2,"Wind_shake":true,"Max_bullet_shells":2,"Snow":true},"Gameplay":{"Allow_party_invites":true,"Camera_animations":1,"Vibration_feedback":true,"Parkour_vaulting":true,"Melee_debug":false,"Toggle_sprint":true,"Auto_parkour":true,"FOV":70,"Toggle_crouch":true,"New_items_fill_the_hotbar":true,"Walkspeed_affects_FOV":true,"Toggle_aim":true,"Aim_sensitivity":1,"Reload_on_empty":true},"Combinations":{"Inspect":[{"_type":"EnumItem","value":102,"enumType":"KeyCode","name":"F"}],"Switch_sight":[{"_type":"EnumItem","value":116,"enumType":"KeyCode","name":"T"}],"Change_alt_firing_mode":[{"_type":"EnumItem","value":98,"enumType":"KeyCode","name":"B"}]},"Crosshair":{"Crosshair_color":{"_type":"Color3","b":0.12941177189350129,"g":1,"r":0.3176470696926117},"Static":false,"Thickness":2,"Transparency":0.9,"Reticle_size":1,"Hitmarker_transparency":0,"Length":12,"Display_lines":true,"Display_dot":false}},"FirstJoinData":{"GotBlitzCoinReward":true},"DailyRewardsClaimed":{"LastClaimDay":20658,"DailyStreak":1,"Day":1},"DropData":[],"Reputation":0,"BadgeData":{"Welcome":true},"Unlocked":{"Stash":0,"Merchant":["SRG-1","MAG-500","Heavy Tactical Armor","Tactical Helmet","Tactical Leggings","AK-47","SPAS-12","Green Combat Inhaler","STIM-PISTOL","Impact Booster"]},"PurchaseData":{"OwnedPasses":[],"PurchaseHistory":[]},"Thirst":0,"StarvationPower":18.600000000000745,"FFDuration":120,"Character":{"Inventory":{"Items":[],"Gear":[{"Name":"Silence Helmet","StatusAttributes":{"FullSet":"Silence"},"Attributes":{"Unbreakable":true,"Type":"Head","NoHats":true,"CantTakeOff":true},"UUID":"b3dde686-77bb-4ec2-9b7d-710e71f3300e"},{"Name":"Silence Leggings","StatusAttributes":{"FullSet":"Silence"},"Attributes":{"Unbreakable":true,"Type":"Legs","NoHats":true,"CantTakeOff":true},"UUID":"c994731c-b009-4544-aa68-3b98f8ac83c0"},{"Name":"Silence Vest","StatusAttributes":{"FullSet":"Silence"},"Attributes":{"Unbreakable":true,"Type":"Body","NoHats":true,"CantTakeOff":true},"UUID":"4eedb98f-3e16-4db2-9733-0073e54cded3"}]},"Body":{"Left Leg":{"isBroken":false,"Health":100,"isMissing":false},"Right Arm":{"isBroken":false,"Health":100,"isMissing":false},"Head":{"isBroken":false,"Health":100,"isMissing":false},"Torso":{"isBroken":false,"Health":100,"isMissing":false},"Right Leg":{"isBroken":false,"Health":100,"isMissing":false},"Left Arm":{"isBroken":false,"Health":100,"isMissing":false}}},"ChallengeData":{"Daily":[{"Type":"Daily","Progress":0,"Desc":"Use throwable items","Completed":false,"LongDesc":"Throw any throwable item you may find","Title":"Utility Specialist","Goal":12,"ID":"{33104839-32ac-40aa-88f4-d4c7b7ce435d}","Conditions":[],"Trigger":"OnThrow","Reward":{"XP":6580,"Bank":26093}},{"Type":"Daily","Progress":0,"Desc":"Lockpick containers","Completed":false,"LongDesc":"Use a lockpick to unlock any container.","Title":"Lockpicker","Goal":14,"ID":"{a96d6627-8a4a-41d3-96fe-5f175909fc82}","Conditions":[],"Trigger":"OnLockpick","Reward":{"XP":6330,"Bank":24165}},{"Type":"Daily","Progress":0,"Desc":"Revive other players","Completed":false,"LongDesc":"Revive other players","Title":"Guardian Angel","Goal":5,"ID":"{832fab99-1308-41ab-aab6-11357f1b298d}","Conditions":{"OnPlayer":true},"Trigger":"OnRevive","Reward":{"XP":5536,"Bank":24718}},{"Type":"Daily","Progress":0,"Desc":"Perform a finisher on players","Completed":false,"LongDesc":"Perform a finisher on any players","Title":"Executioner","Goal":12,"ID":"{7a7abd4d-df90-4822-b227-bbdcf7ed7f06}","Conditions":{"OnPlayer":true},"Trigger":"OnFinish","Reward":{"XP":5882,"Bank":20193}}],"Custom":[],"Weekly":[{"Type":"Weekly","Progress":0,"Desc":"Turn in $20000 worth of valuables","Completed":false,"LongDesc":"Turn in $20000 worth of valuables at once at any broker","Title":"Risky Collector","Goal":2,"ID":"{077b73ea-ea71-4fa1-a5fb-6657787d741a}","Conditions":{"Amount":20000},"Trigger":"OnValuablesTrade","Reward":{"XP":23661,"Bank":77070}},{"Type":"Weekly","Progress":0,"Desc":"Perform a finisher on enemies","Completed":false,"LongDesc":"Perform a finisher on any enemy","Title":"Cold Blooded","Goal":19,"ID":"{0355f31a-e970-4011-ba42-32f7855a2a6e}","Conditions":[],"Trigger":"OnFinisher","Reward":{"XP":20902,"Bank":82651}},{"Type":"Weekly","Progress":0,"Desc":"Kill players from 300+ studs","Completed":false,"LongDesc":"Kill any player from 300+ studs away","Title":"Long shot","Goal":9,"ID":"{c9b66665-cba0-4721-bca9-61ffb98a0036}","Conditions":{"OnPlayer":true,"Distance":300},"Trigger":"OnKill","Reward":{"XP":22176,"Bank":117361}},{"Type":"Weekly","Progress":0,"Desc":"Kill players without dying","Completed":false,"LongDesc":"Kill enough players without dying","Title":"Rampage","Goal":13,"ID":"{418d4bc6-f597-4096-9d69-7e98d8a61d72}","Conditions":{"OnPlayer":true},"Trigger":"OnKill","Reward":{"XP":25099,"Bank":120916}}],"DailyRefresh":20658,"WeeklyRefresh":2951},"hasJoined":false,"Journal":{"Terminals":true,"Merchant":true,"Outlanders":true,"Brokers":true,"██████ Transcript":true},"Level":4,"CombatLogged":false,"Bank":358615,"RewardsClaimed":{"newStarterPack":true},"Bounty":21312,"BlitzCredit":7,"DehydrationPower":25,"Credits":9800,"Cosmetics":{"GamepassData":{"EmoteSlotExpansion":false},"Data":{"Emote":["Cheer","Laugh","Point","Wave","Sit","Sturdy","Griddy","Rushin","Whip","Parker","Baroque","Unforgettable"],"Charm":["Rebel Tag"],"Skin":["Tomahawk_Starbreaker"],"Finisher":["Default","Tomahawk","Katana"],"Pose":["Default"],"LootBox":[]},"Equipped":{"Finisher":["Katana"],"Charm":[],"Skin":[],"Pose":["Default"],"Emote":[]}},"Xp":6635,"WeaponLevelData":[],"State":{"MetBlitz":false,"MetScourge":false,"MetContrabandExchanger":false},"Valuables":55671,"Influence":10,"LastKnownPosition":{"_type":"Vector3","x":-483.47613525390627,"y":447.6396484375,"z":28.258243560791017},"Hunger":30.6299999999993,"Stash":[{"UUID":"75818ffc-311d-4540-b404-589ba048e9de","Name":"Red Keycard","Attributes":{"DisableDropping":true,"UsesLeft":1}},{"UUID":"5cf6ddb0-7a2f-43c0-8c2a-7a6959e600cb","Name":"Red Keycard","Attributes":{"DisableDropping":true,"UsesLeft":1}},{"UUID":"2e9d060e-a350-4192-a6af-b84062838625","Name":"Green Keycard","Attributes":{"DisableDropping":true,"UsesLeft":1}},{"UUID":"3bdfe588-afc1-4da8-b286-ca0f992137ad","Name":"Green Keycard","Attributes":{"DisableDropping":true,"UsesLeft":1}},{"UUID":"df4da850-b309-439f-90f9-3b5098e2d2a3","Name":"Green Keycard","Attributes":{"DisableDropping":true,"UsesLeft":1}},{"Name":"Green Flare Gun","StatusAttributes":{"MagazineCapacity":1,"Magazine":1,"AmmoType":0,"Mode":1,"Ammo":0,"CurrentSight":1,"SpareMagazines":0},"Attributes":{"DisableDropping":true},"UUID":"03a5ca15-e2a3-4c99-a755-30adcb697450"},{"Name":"RSH-12","StatusAttributes":{"MagazineCapacity":5,"Magazine":4,"AmmoType":1,"Mode":1,"Ammo":0,"CurrentSight":1,"SpareMagazines":4},"Attributes":{"DisableDropping":true},"UUID":"bf9efcdc-4fd6-4924-b4a0-bec91659bf2c"},{"UUID":"28b97e09-05e1-4662-a226-8b3a56d6a3d1","Name":"Purple Keycard","Attributes":{"UsesLeft":1}},{"Name":"Light Tactical Armor","StatusAttributes":{"FullSet":"Operator"},"Attributes":{"Unbreakable":true,"Type":"Body"},"UUID":"36fd0e41-d1a6-4637-a3ab-33b303644102"},{"UUID":"30f2caa9-cf46-420d-8eff-794908a907b7","Name":"Purple Keycard","Attributes":{"UsesLeft":1}},{"UUID":"642e8379-4050-4930-921a-3d352c124c1e","Name":"Green Keycard","Attributes":{"UsesLeft":1}},{"UUID":"ec991df5-dfb9-4603-aa67-c278126c1de9","Name":"Purple Keycard","Attributes":{"UsesLeft":1}},{"Name":"Light Tactical Armor","StatusAttributes":{"FullSet":"Operator"},"Attributes":{"Unbreakable":true,"Type":"Body"},"UUID":"749fbe1c-dab4-4896-aaca-625e62102399"},{"Name":"Operator Helmet","StatusAttributes":{"FullSet":"Operator"},"Attributes":{"Unbreakable":true,"Type":"Head","NoHats":true,"CantTakeOff":true},"UUID":"a6fa0b30-cfef-426c-a92f-0a0b84111f58"},{"UUID":"e37bd6e4-0c53-43fe-bcc6-e056fb5bc106","Name":"Sentry Turret","Attributes":{"Stackable":true,"Consumable":true}},{"UUID":"c6e97534-48a0-4b63-ad68-41898f1cd2f4","Name":"Sentry Turret","Attributes":{"Stackable":true,"Consumable":true}},{"UUID":"a82cb2c3-6a3b-4022-bd5e-471973c25676","Name":"Sentry Turret","Attributes":{"Stackable":true,"Consumable":true}},{"Name":"Light Tactical Armor","StatusAttributes":{"FullSet":"Operator"},"Attributes":{"Unbreakable":true,"Type":"Body"},"UUID":"bb3490da-7004-4998-8594-090bd3336709"},{"Name":"Bladedancer Helmet","StatusAttributes":{"FullSet":"Commander"},"Attributes":{"Type":"Head","CantTakeOff":true,"Unbreakable":true,"NoHats":true,"DisableDropping":true},"UUID":"16e05202-b852-460e-a14f-8cf7acd42c5a"},{"Name":"Operator Vest","StatusAttributes":{"FullSet":"Operator"},"Attributes":{"Unbreakable":true,"Type":"Body","NoHats":true,"CantTakeOff":true},"UUID":"121cf84f-76a7-4a34-93e6-246ff301a1c6"},{"UUID":"00174dbd-cc90-45a0-8147-fe6979a78916","Name":"P90-Z","StatusAttributes":{"MagazineCapacity":50,"Magazine":50,"AmmoType":1,"Mode":1,"Ammo":177,"CurrentSight":1,"SpareMagazines":4}},{"UUID":"d182bbdd-a154-42cf-bfaa-cfdb92fb0bb6","Name":"RSH-12","StatusAttributes":{"MagazineCapacity":5,"Magazine":4,"AmmoType":1,"Mode":1,"Ammo":0,"CurrentSight":1,"SpareMagazines":4}},{"Name":"Photon Blades","StatusAttributes":{"Durability":91.5,"Broken":false},"Attributes":{"Durability":91.5,"Walkspeed":3,"Broken":false},"UUID":"2f4a4019-46a5-47b2-8fd6-c621001164ce"},{"UUID":"71e959ef-bd3f-4a4e-aec2-f81e7009fba5","Name":"Blue Keycard","Attributes":{"UsesLeft":2}},{"Name":"Light Tactical Armor","StatusAttributes":{"FullSet":"Operator"},"Attributes":{"Unbreakable":true,"Type":"Body"},"UUID":"31061d68-7972-4337-80f3-2c91bdc9f9d1"}],"WeaponData":{"MP5":[300,2],"P90-Z":[250,1],"RSH-12":[400,1],"STIM-PISTOL":[300,1],"Photon Alternator":[275,1],"AK-47":[675,1],"Photon Blades":[780,2],"SRG-1":[175,2],"MAG-500":[1950,3]},"Cash":37850}